django_massmedia-1.2.10.dist-info/DESCRIPTION.rst
django_massmedia-1.2.10.dist-info/METADATA
django_massmedia-1.2.10.dist-info/metadata.json
django_massmedia-1.2.10.dist-info/RECORD
django_massmedia-1.2.10.dist-info/top_level.txt
django_massmedia-1.2.10.dist-info/WHEEL
massmedia/__init__.py
massmedia/admin.py
massmedia/base_models.py
massmedia/fields.py
massmedia/forms.py
massmedia/models.py
massmedia/resize.py
massmedia/settings.py
massmedia/urls.py
massmedia/utils.py
massmedia/views.py
massmedia/youtube.py
massmedia/fixtures/initial_data.json
massmedia/fixtures/test_images.json
massmedia/locale/fr/LC_MESSAGES/django.po
massmedia/management/__init__.py
massmedia/management/commands/__init__.py
massmedia/management/commands/import_images.py
massmedia/metadata/__init__.py
massmedia/metadata/archive.py
massmedia/metadata/audio.py
massmedia/metadata/config.py
massmedia/metadata/file_system.py
massmedia/metadata/filter.py
massmedia/metadata/formatter.py
massmedia/metadata/image.py
massmedia/metadata/image_metadata.py
massmedia/metadata/jpeg.py
massmedia/metadata/metadata.py
massmedia/metadata/metadata_item.py
massmedia/metadata/misc.py
massmedia/metadata/program.py
massmedia/metadata/register.py
massmedia/metadata/riff.py
massmedia/metadata/safe.py
massmedia/metadata/setter.py
massmedia/metadata/timezone.py
massmedia/metadata/utils.py
massmedia/metadata/video.py
massmedia/metadata/parser/__init__.py
massmedia/metadata/parser/png.py
massmedia/metadata/qt/__init__.py
massmedia/migrations/0001_initial.py
massmedia/migrations/0002_add_contenttype_field.py
massmedia/migrations/0003_imagecustomsize.py
massmedia/migrations/__init__.py
massmedia/static/.DS_Store
massmedia/static/massmedia/.DS_Store
massmedia/static/massmedia/css/cropperwindow.css
massmedia/static/massmedia/css/jsmodal-dark.css
massmedia/static/massmedia/css/jsmodal-light.css
massmedia/static/massmedia/images/.DS_Store
massmedia/static/massmedia/images/jsmodal-logo.png
massmedia/static/massmedia/images/jsmodal/loading.gif
massmedia/static/massmedia/images/jsmodal/modal-close.png
massmedia/static/massmedia/js/cropper.js
massmedia/static/massmedia/js/genericcollections.js
massmedia/static/massmedia/js/jsmodal-1.0d.js
