Metadata-Version: 2.0
Name: django-massmedia
Version: 1.2.10
Summary: Allows for site staff can upload and edit the media files through the site, and the filesystem is maintained in the background.
Home-page: http://github.com/washingtontimes/django-massmedia
Author: Justin Quick
Author-email: jquick@washingtontimes.com
License: UNKNOWN
Platform: UNKNOWN
Requires-Dist: gdata
Requires-Dist: simplejson
Requires-Dist: django-mathfilters (==0.3.0)
Requires-Dist: IPTCInfo
Requires-Dist: hachoir-metadata
Requires-Dist: hachoir-core
Requires-Dist: hachoir-parser
